inflector/__init__.py
inflector/languages/__init__.py
inflector/languages/base.py
inflector/languages/english.py
inflector/languages/spanish.py
Inflector-3.0.1.dist-info/LICENSE
Inflector-3.0.1.dist-info/METADATA
Inflector-3.0.1.dist-info/WHEEL
Inflector-3.0.1.dist-info/top_level.txt
Inflector-3.0.1.dist-info/RECORD
