Metadata-Version: 2.1
Name: Inflector
Version: 3.0.1
Summary: Inflector for Python
Home-page: https://github.com/ixmatus/inflector
Author: Parnell Springmeyer
Author-email: parnell@digitalmentat.com
Keywords: inflector text language english
Classifier: Intended Audience :: Developers
Classifier: License :: OSI Approved :: Python Software Foundation License
Classifier: Programming Language :: Python
Classifier: Topic :: Software Development :: Libraries :: Python Modules
License-File: LICENSE
